{
  "id": 3917,
  "name": "Kakheti",
  "state_code": "KA",
  "cities": [
    {
      "id": 106456,
      "name": "Akhmet’a"
    },
    {
      "id": 106457,
      "name": "Akhmet’is Munitsip’alit’et’i"
    },
    {
      "id": 106458,
      "name": "Gurjaani"
    },
    {
      "id": 106459,
      "name": "Lagodekhi"
    },
    {
      "id": 106460,
      "name": "Qvareli"
    },
    {
      "id": 106461,
      "name": "Sagarejo"
    },
    {
      "id": 106462,
      "name": "Sighnaghi"
    },
    {
      "id": 106463,
      "name": "Sighnaghis Munitsip’alit’et’i"
    },
    {
      "id": 106464,
      "name": "Telavi"
    },
    {
      "id": 106465,
      "name": "Tsinandali"
    },
    {
      "id": 106466,
      "name": "Tsnori"
    }
  ]
}