{
  "id": 4131,
  "name": "Santa Bárbara Department",
  "state_code": "SB",
  "cities": [
    {
      "id": 115806,
      "name": "Agualote"
    },
    {
      "id": 115807,
      "name": "Arada"
    },
    {
      "id": 115808,
      "name": "Atima"
    },
    {
      "id": 115809,
      "name": "Azacualpa"
    },
    {
      "id": 115810,
      "name": "Berlín"
    },
    {
      "id": 115811,
      "name": "Callejones"
    },
    {
      "id": 115812,
      "name": "Camalote"
    },
    {
      "id": 115813,
      "name": "Casa Quemada"
    },
    {
      "id": 115814,
      "name": "Ceguaca"
    },
    {
      "id": 115815,
      "name": "Chinda"
    },
    {
      "id": 115816,
      "name": "Concepción del Norte"
    },
    {
      "id": 115817,
      "name": "Concepción del Sur"
    },
    {
      "id": 115818,
      "name": "Correderos"
    },
    {
      "id": 115819,
      "name": "El Ciruelo"
    },
    {
      "id": 115820,
      "name": "El Corozal"
    },
    {
      "id": 115821,
      "name": "El Mochito"
    },
    {
      "id": 115822,
      "name": "El Níspero"
    },
    {
      "id": 115823,
      "name": "Guacamaya"
    },
    {
      "id": 115824,
      "name": "Gualala"
    },
    {
      "id": 115825,
      "name": "Gualjoco"
    },
    {
      "id": 115826,
      "name": "Ilama"
    },
    {
      "id": 115827,
      "name": "Joconal"
    },
    {
      "id": 115828,
      "name": "La Flecha"
    },
    {
      "id": 115829,
      "name": "Laguna Verde"
    },
    {
      "id": 115830,
      "name": "Las Vegas"
    },
    {
      "id": 115831,
      "name": "Las Vegas Santa Barbara"
    },
    {
      "id": 115832,
      "name": "Loma Alta"
    },
    {
      "id": 115833,
      "name": "Macuelizo"
    },
    {
      "id": 115834,
      "name": "Naco"
    },
    {
      "id": 115835,
      "name": "Naranjito"
    },
    {
      "id": 115836,
      "name": "Nueva Frontera"
    },
    {
      "id": 115837,
      "name": "Nueva Jalapa"
    },
    {
      "id": 115838,
      "name": "Nuevo Celilac"
    },
    {
      "id": 115839,
      "name": "Petoa"
    },
    {
      "id": 115840,
      "name": "Pinalejo"
    },
    {
      "id": 115841,
      "name": "Protección"
    },
    {
      "id": 115842,
      "name": "Quimistán"
    },
    {
      "id": 115843,
      "name": "San Francisco de Ojuera"
    },
    {
      "id": 115844,
      "name": "San José de Colinas"
    },
    {
      "id": 115845,
      "name": "San José de Tarros"
    },
    {
      "id": 115846,
      "name": "San Luis"
    },
    {
      "id": 115847,
      "name": "San Luis de Planes"
    },
    {
      "id": 115848,
      "name": "San Marcos"
    },
    {
      "id": 115849,
      "name": "San Nicolás"
    },
    {
      "id": 115850,
      "name": "San Pedro Zacapa"
    },
    {
      "id": 115851,
      "name": "San Vicente Centenario"
    },
    {
      "id": 115852,
      "name": "Santa Bárbara"
    },
    {
      "id": 115853,
      "name": "Santa Rita"
    },
    {
      "id": 115854,
      "name": "Sula"
    },
    {
      "id": 115855,
      "name": "Tras Cerros"
    },
    {
      "id": 115856,
      "name": "Trinidad"
    }
  ]
}