{
  "id": 5704,
  "name": "Cajamarca",
  "state_code": "CAJ",
  "cities": [
    {
      "id": 153957,
      "name": "Bambamarca"
    },
    {
      "id": 153958,
      "name": "Bellavista"
    },
    {
      "id": 153959,
      "name": "Cajabamba"
    },
    {
      "id": 153960,
      "name": "Cajamarca"
    },
    {
      "id": 153961,
      "name": "Celendín"
    },
    {
      "id": 153962,
      "name": "Chota"
    },
    {
      "id": 153963,
      "name": "Jaén"
    },
    {
      "id": 153964,
      "name": "Provincia de Cajabamba"
    },
    {
      "id": 153965,
      "name": "Provincia de Cajamarca"
    },
    {
      "id": 153966,
      "name": "Provincia de Celendín"
    },
    {
      "id": 153967,
      "name": "Provincia de Chota"
    },
    {
      "id": 153968,
      "name": "Provincia de Contumazá"
    },
    {
      "id": 153969,
      "name": "Provincia de Cutervo"
    },
    {
      "id": 153970,
      "name": "Provincia de Hualgayoc"
    },
    {
      "id": 153971,
      "name": "Provincia de Jaén"
    },
    {
      "id": 153972,
      "name": "Provincia de San Ignacio"
    },
    {
      "id": 153973,
      "name": "Provincia de San Miguel"
    },
    {
      "id": 153974,
      "name": "Provincia de Santa Cruz"
    },
    {
      "id": 153975,
      "name": "San Ignacio"
    }
  ]
}